{   
    "https://jobs.grob-aircraft.com/": {
        "title": "Startseite - Grob Aircraft SE",
        "first_seen": "2026-06-02",
        "posted_date": "",
        "score": 45,
        "company": "Grob Aircraft"
    },
    "https://jobs.grob-aircraft.com/jobs/7662535-flight-dynamics-modelling-engineer-m-f-x-ca-1-europa": {
        "title": "Flight Dynamics Modelling Engineer (m/f/x) - CA-1 Europa - Grob Aircraft SE",
        "first_seen": "2026-06-02",
        "posted_date": "",
        "score": 125,
        "company": "Grob Aircraft"
    },
    "https://jobs.grob-aircraft.com/jobs/7814453-simulation-flight-model-developer-m-f-x": {
        "title": "Simulation Flight Model Developer (m/f/x) - Grob Aircraft SE",
        "first_seen": "2026-06-02",
        "posted_date": "",
        "score": 105,
        "company": "Grob Aircraft"
    },
    "https://www.liebherr.com/en-int/careers/professionals/research-and-development-5370622": {
        "title": "Research and development jobs",
        "first_seen": "2026-06-02",
        "posted_date": "",
        "score": 55,
        "company": "liebherr"
    },
    "https://jobs.everllence.com/search/": {
        "title": "everllence - Stellen",
        "first_seen": "2026-06-02",
        "posted_date": "",
        "score": 80,
        "company": "Everllence"
    },
    "https://jobs.everllence.com/search/?createNewAlert=false&q=&optionsFacetsDD_city=&optionsFacetsDD_customfield1=&optionsFacetsDD_customfield2=": {
        "title": "everllence - Stellen",
        "first_seen": "2026-06-02",
        "posted_date": "",
        "score": 80,
        "company": "Everllence"
    },
    "https://jobs.siemens.com/en_US/externaljobs/SearchJobs/?42386=%5B812132%5D&42386_format=17546&42389=%5B39106405%2C144468627%2C102122%2C102134%2C102127%5D&42389_format=17549&42390=%5B102155%2C102156%2C102157%2C102158%5D&42390_format=17550&listFilterMode=1&folderRecordsPerPage=6&folderOffset=12": {
        "title": "Job Search | Careers Marketplace - Siemens",
        "first_seen": "2026-06-02",
        "posted_date": "",
        "score": 45,
        "company": "Siemens"
    },
    "https://www.simtecto.de/jobs-karriere.html": {
        "title": "Jobs / Karriere - Simtecto",
        "first_seen": "2026-06-02",
        "posted_date": "",
        "score": 110,
        "company": "Simtecto"
    },
    "https://www.simtecto.de/jobs-karriere.html#skipNavigation253": {
        "title": "Jobs / Karriere - Simtecto",
        "first_seen": "2026-06-02",
        "posted_date": "",
        "score": 110,
        "company": "Simtecto"
    },
    "https://www.simtecto.de/jobs-karriere.html#skipNavigation254": {
        "title": "Jobs / Karriere - Simtecto",
        "first_seen": "2026-06-02",
        "posted_date": "",
        "score": 110,
        "company": "Simtecto"
    },
    "https://k21840.coveto.de/job-design-ingenieur-in-im-lht-entwicklungsbetrieb-m-w-d-lufthansa-technik-hamburg-14127.html": {
        "title": "Jobs: Design-Ingenieur_in im LHT-Entwicklungsbetrieb (m/w/d) Lufthansa Technik in Hamburg | Aviation Industry Personnel SERVICES GmbH",
        "first_seen": "2026-06-02",
        "posted_date": "",
        "score": 95,
        "company": "AIP Services"
    },
    "https://job-boards.eu.greenhouse.io/rocketfactoryaugsburgag": {
        "title": "Jobs at Rocket Factory Augsburg AG",
        "first_seen": "2026-06-02",
        "posted_date": "",
        "score": 60,
        "company": "Rocket Factory"
    },
    "https://job-boards.eu.greenhouse.io/rocketfactoryaugsburgag/jobs/4828814101": {
        "title": "Job Application for Avionics Engineer - Design (m/f/d) at Rocket Factory Augsburg AG",
        "first_seen": "2026-06-02",
        "posted_date": "",
        "score": 45,
        "company": "Rocket Factory"
    },
    "https://job-boards.eu.greenhouse.io/rocketfactoryaugsburgag/jobs/4833743101": {
        "title": "Job Application for Propulsion Test Technician at Rocket Factory Augsburg AG",
        "first_seen": "2026-06-02",
        "posted_date": "",
        "score": 45,
        "company": "Rocket Factory"
    },
    "https://www.kelvion.com/de/karriere/jobs/detail/konstrukteurin-konstruktionstechnikerin": {
        "title": "Detail | Kelvion",
        "first_seen": "2026-06-02",
        "posted_date": "",
        "score": 45,
        "company": "Kelvion"
    },
    "https://karriere.ziehl-abegg.de/detail/job/69ce66e0bf5ebf7c8729dac9": {
        "title": "Entwicklungsingenieur (m/w/d)",
        "first_seen": "2026-06-02",
        "posted_date": "",
        "score": 80,
        "company": "Ziehl"
    },
    "https://helsing.ai/jobs": {
        "title": "Jobs \u2013 Helsing",
        "first_seen": "2026-06-02",
        "posted_date": "",
        "score": 60,
        "company": "Helsing"
    }
}